{
  "equipos": [
    "Escuadra Alpha",
    "Escuadra Phantom",
    "Escuadra Nova",
    "Escuadra Shadow",
    "Escuadra Viper",
    "Escuadra Raptor",
    "Escuadra Foxtrot",
    "Escuadra Yankee",
    "Escuadra Bravo",
    "Escuadra Hawk",
    "Escuadra Titan",
    "Escuadra Echo",
    "Escuadra Maverick",
    "Escuadra Delta",
    "Escuadra Lima",
    "Escuadra Ghost",
    "Escuadra Jaguar",
    "Escuadra Zulu",
    "Escuadra Charlie",
    "Escuadra Wolf",
    "Escuadra Orion",
    "Escuadra Spartan",
    "Escuadra Xray",
    "Escuadra Kilo"
  ],
  "octavos": [
    "Escuadra Alpha",
    "Escuadra Nova",
    "Escuadra Viper",
    "Escuadra Foxtrot",
    "Escuadra Bravo",
    "Escuadra Titan",
    "Escuadra Maverick",
    "Escuadra Lima",
    "Escuadra Jaguar",
    "Escuadra Charlie",
    "Escuadra Orion",
    "Escuadra Xray"
  ],
  "repechaje": [
    "Escuadra Raptor",
    "Escuadra Echo",
    "Escuadra Phantom",
    "Escuadra Hawk",
    "Escuadra Shadow",
    "Escuadra Yankee"
  ],
  "cuartos": [
    "Escuadra Orion",
    "Escuadra Xray",
    "Escuadra Maverick",
    "Escuadra Shadow",
    "Escuadra Titan",
    "Escuadra Alpha",
    "Escuadra Lima",
    "Escuadra Nova"
  ],
  "semifinal": [
    "Escuadra Orion",
    "Escuadra Maverick",
    "Escuadra Titan",
    "Escuadra Lima"
  ],
  "final": [
    "Escuadra Titan",
    "Escuadra Lima"
  ],
  "podio": {
    "oro": "Escuadra Titan",
    "plata": "Escuadra Lima",
    "bronce": "Escuadra Orion"
  }
}